LICENSE
MANIFEST.in
README.md
salesforce_bulk_api.py
setup.cfg
setup.py
test_bulk_salesforce.py
salesforce_bulk_api.egg-info/PKG-INFO
salesforce_bulk_api.egg-info/SOURCES.txt
salesforce_bulk_api.egg-info/dependency_links.txt
salesforce_bulk_api.egg-info/requires.txt
salesforce_bulk_api.egg-info/top_level.txt