Metadata-Version: 1.1
Name: salesforce-bulk-api
Version: 1.2.0
Summary: A Python 2 and 3 interface to the Salesforce Bulk API.
Home-page: https://github.com/safarijv/salesforce-bulk-api
Author: Chris Guidry
Author-email: cguidry@oreilly.com
License: BSD
Platform: UNKNOWN
Classifier: Programming Language :: Python :: 2
Classifier: Programming Language :: Python :: 2.7
Classifier: Programming Language :: Python :: 3
Classifier: Programming Language :: Python :: 3.1
Classifier: Programming Language :: Python :: 3.3
Classifier: Programming Language :: Python :: 3.4
Classifier: Programming Language :: Python :: Implementation :: CPython
Classifier: Programming Language :: Python :: Implementation :: PyPy
Classifier: Intended Audience :: Developers
Classifier: License :: OSI Approved :: BSD License
Classifier: Topic :: Office/Business :: Groupware
Classifier: Topic :: Software Development :: Libraries
Classifier: Topic :: Utilities
